zipline_bitmex/__init__.py
zipline_bitmex/bitmex_bundle.py
zipline_bitmex/bitmex_calendar.py
zipline_bitmex-0.1.2.dist-info/LICENSE
zipline_bitmex-0.1.2.dist-info/METADATA
zipline_bitmex-0.1.2.dist-info/WHEEL
zipline_bitmex-0.1.2.dist-info/top_level.txt
zipline_bitmex-0.1.2.dist-info/RECORD
