Metadata-Version: 2.1
Name: zipline-bitmex
Version: 0.1.2
Summary: BitMEX bundle for Zipline
Home-page: https://github.com/nerdDan/zipline-bitmex
Author: Daniel Zhou
Author-email: danichau93@gmail.com
License: GPL
Platform: UNKNOWN
Classifier: Development Status :: 2 - Pre-Alpha
Classifier: Intended Audience :: Financial and Insurance Industry
Classifier: License :: OSI Approved :: GNU General Public License v3 (GPLv3)
Classifier: Operating System :: OS Independent
Classifier: Programming Language :: Python :: 3.4
Classifier: Topic :: Office/Business :: Financial :: Investment
